helperlibs/__init__.py
helperlibs/bio/__init__.py
helperlibs/bio/featurematch.py
helperlibs/bio/seqio.py
helperlibs/tests/__init__.py
helperlibs/tests/bio/__init__.py
helperlibs/tests/bio/test_featurematch.py
helperlibs/tests/bio/test_seqio.py
helperlibs/tests/wrappers/__init__.py
helperlibs/tests/wrappers/test_io.py
helperlibs/wrappers/__init__.py
helperlibs/wrappers/io.py
helperlibs-0.2.2.dist-info/licenses/LICENSE.txt
helperlibs-0.2.2.dist-info/METADATA
helperlibs-0.2.2.dist-info/WHEEL
helperlibs-0.2.2.dist-info/top_level.txt
helperlibs-0.2.2.dist-info/RECORD
