Metadata-Version: 2.4
Name: helperlibs
Version: 0.2.2
Summary: A collection of bioinformatics-related helper functions
Home-page: https://github.com/kblin/bioinf-helperlibs/wiki
Author: Kai Blin
Author-email: kblin@biosustain.dtu.dk
License: GPL
Keywords: bioinformatics
Classifier: Development Status :: 3 - Alpha
Classifier: Topic :: Scientific/Engineering :: Bio-Informatics
Classifier: License :: OSI Approved :: GNU General Public License v3 or later (GPLv3+)
Classifier: Programming Language :: Python :: 3
Classifier: Programming Language :: Python :: 3.11
Classifier: Programming Language :: Python :: 3.12
Classifier: Programming Language :: Python :: 3.13
License-File: LICENSE.txt
Requires-Dist: Biopython>=1.76
Provides-Extra: testing
Requires-Dist: flake8; extra == "testing"
Requires-Dist: minimock; extra == "testing"
Requires-Dist: pytest; extra == "testing"
Requires-Dist: pytest-cover; extra == "testing"
Dynamic: author
Dynamic: author-email
Dynamic: classifier
Dynamic: description
Dynamic: description-content-type
Dynamic: home-page
Dynamic: keywords
Dynamic: license
Dynamic: license-file
Dynamic: provides-extra
Dynamic: requires-dist
Dynamic: summary
